django_tree_view/README.md
django_tree_view/RELEASE_NOTES.md
django_tree_view/VERSION
django_tree_view/__init__.py
django_tree_view/module_tree.py
django_tree_view/path_resolver.py
django_tree_view/utils.py
django_tree_view/view.py
django_tree_view/view_tree.py
django_tree_view/__pycache__/__init__.cpython-36.pyc
django_tree_view/__pycache__/__init__.cpython-37.pyc
django_tree_view/__pycache__/__init__.cpython-38.pyc
django_tree_view/__pycache__/module_tree.cpython-36.pyc
django_tree_view/__pycache__/module_tree.cpython-37.pyc
django_tree_view/__pycache__/path_resolver.cpython-36.pyc
django_tree_view/__pycache__/path_resolver.cpython-37.pyc
django_tree_view/__pycache__/path_resolver.cpython-38.pyc
django_tree_view/__pycache__/utils.cpython-36.pyc
django_tree_view/__pycache__/utils.cpython-38.pyc
django_tree_view/__pycache__/view.cpython-36.pyc
django_tree_view/__pycache__/view.cpython-37.pyc
django_tree_view/__pycache__/view.cpython-38.pyc
django_tree_view/__pycache__/view_tree.cpython-36.pyc
django_tree_view/__pycache__/view_tree.cpython-38.pyc
django_tree_view/tests/__init__.py
django_tree_view/tests/tests.py
django_tree_view/tests/urls.py
django_tree_view-4.3.0.dist-info/LICENSE
django_tree_view-4.3.0.dist-info/METADATA
django_tree_view-4.3.0.dist-info/WHEEL
django_tree_view-4.3.0.dist-info/top_level.txt
django_tree_view-4.3.0.dist-info/RECORD
