Metadata-Version: 2.1
Name: django-tree-view
Version: 4.3.0
Summary: Organize your code and templates in a natural directory structure
Home-page: https://github.com/quadrant-newmedia/django_tree_view
Author: Alex Fischer
Author-email: alex@quadrant.net
License: UNKNOWN
Platform: UNKNOWN
Classifier: Programming Language :: Python :: 3
Classifier: License :: OSI Approved :: MIT License
Classifier: Operating System :: OS Independent
Requires-Python: >=3.7
Requires-Dist: Django (<6,>=3.0)
Requires-Dist: django-dynamic-path (<1)
Requires-Dist: django-referer-csrf (<1)
Requires-Dist: django-early-return (<1)
